LICENCE
README.md
setup.py
generate_lib/__init__.py
generate_lib/generate_lib.py
generate_lib.egg-info/PKG-INFO
generate_lib.egg-info/SOURCES.txt
generate_lib.egg-info/dependency_links.txt
generate_lib.egg-info/requires.txt
generate_lib.egg-info/top_level.txt