Metadata-Version: 2.1
Name: generate-lib
Version: 0.0.1
Summary: Keywords lib to robotframework
Author: Kaio Cândido Santiago
Author-email: kaio.santiago.13@hotmail.com
License: MIT License
Keywords: generate lib robot framework
License-File: LICENCE
